flights/__init__.py
flights/server.py
flights/api/__init__.py
flights/api/client.py
flights/api/endpoints.py
flights/config/__init__.py
flights/config/api.py
flights/models/flight_search.py
flights/models/multi_city.py
flights/models/offers.py
flights/models/search.py
flights/models/segments.py
flights/models/time_specs.py
flights/services/__init__.py
flights/services/search.py
mseep_flights_mcp-0.1.4.dist-info/METADATA
mseep_flights_mcp-0.1.4.dist-info/WHEEL
mseep_flights_mcp-0.1.4.dist-info/entry_points.txt
mseep_flights_mcp-0.1.4.dist-info/licenses/LICENSE
mseep_flights_mcp-0.1.4.dist-info/RECORD
